microsoft_graph_helpers/__init__.py
microsoft_graph_helpers/api_token.py
microsoft_graph_helpers/core.py
microsoft_graph_helpers/email.py
microsoft_graph_helpers/groups.py
microsoft_graph_helpers/security.py
microsoft_graph_helpers/users.py
microsoft_graph_helpers-0.1.2.dist-info/METADATA
microsoft_graph_helpers-0.1.2.dist-info/WHEEL
microsoft_graph_helpers-0.1.2.dist-info/top_level.txt
microsoft_graph_helpers-0.1.2.dist-info/RECORD
