Metadata-Version: 2.4
Name: microsoft_graph_helpers
Version: 0.1.2
Summary: Helper functions for interacting with Microsoft Graph API
Author: Lucas Krupinski
License: MIT
Requires-Python: >=3.10
Requires-Dist: requests>=2.32.5
Dynamic: requires-python
